vectordbcloud/__init__.py
vectordbcloud/__init___optimized.py
vectordbcloud/client.py
vectordbcloud/client_optimized.py
vectordbcloud/client_updated.py
vectordbcloud/ecp.py
vectordbcloud/endpoints_extended.py
vectordbcloud/exceptions.py
vectordbcloud/fireducks_implementation.py
vectordbcloud/models.py
vectordbcloud-3.0.3.dist-info/licenses/LICENSE
vectordbcloud-3.0.3.dist-info/METADATA
vectordbcloud-3.0.3.dist-info/WHEEL
vectordbcloud-3.0.3.dist-info/top_level.txt
vectordbcloud-3.0.3.dist-info/RECORD
