Metadata-Version: 2.4
Name: vectordbcloud
Version: 3.0.3
Summary: VectorDBCloud Python SDK - 209 Endpoints (AWS Verified) - 100% ECP-Native - Fireducks + Falcon + Pydantic - <5ms + >100k users
Home-page: https://github.com/VectorDBCloud/python-sdk
Author: VectorDBCloud
Author-email: support@vectordbcloud.com
Project-URL: Documentation, https://docs.vectordbcloud.com
Project-URL: Source, https://github.com/VectorDBCloud/python-sdk
Project-URL: Tracker, https://github.com/VectorDBCloud/python-sdk/issues
Keywords: vectordb database api sdk python ecp ephemeral-context-protocol
Classifier: Development Status :: 5 - Production/Stable
Classifier: Intended Audience :: Developers
Classifier: License :: OSI Approved :: MIT License
Classifier: Programming Language :: Python :: 3
Classifier: Programming Language :: Python :: 3.8
Classifier: Programming Language :: Python :: 3.9
Classifier: Programming Language :: Python :: 3.10
Classifier: Programming Language :: Python :: 3.11
Classifier: Programming Language :: Python :: 3.12
Classifier: Topic :: Software Development :: Libraries :: Python Modules
Classifier: Topic :: Database
Classifier: Topic :: Scientific/Engineering :: Artificial Intelligence
Requires-Python: >=3.8
License-File: LICENSE
Requires-Dist: falcon==3.1.1
Requires-Dist: pydantic<2.0,>=1.10.8
Requires-Dist: aiohttp>=3.8.0
Requires-Dist: uvloop>=0.17.0
Requires-Dist: requests>=2.28.0
Requires-Dist: urllib3>=1.26.0
Requires-Dist: numpy>=1.21.0
Requires-Dist: pandas>=1.3.0
Requires-Dist: typing-extensions>=4.0.0
Requires-Dist: certifi>=2022.0.0
Requires-Dist: charset-normalizer>=2.0.0
Requires-Dist: idna>=3.0.0
Requires-Dist: tenacity>=8.2.2
Requires-Dist: cachetools>=5.3.0
Requires-Dist: orjson>=3.8.12
Requires-Dist: ujson>=5.7.0
Provides-Extra: dev
Requires-Dist: pytest>=7.0.0; extra == "dev"
Requires-Dist: pytest-asyncio>=0.21.0; extra == "dev"
Requires-Dist: black>=22.0.0; extra == "dev"
Dynamic: author
Dynamic: author-email
Dynamic: classifier
Dynamic: description
Dynamic: description-content-type
Dynamic: home-page
Dynamic: keywords
Dynamic: license-file
Dynamic: project-url
Dynamic: provides-extra
Dynamic: requires-dist
Dynamic: requires-python
Dynamic: summary
